odoo/addons/project_stock/README.rst
odoo/addons/project_stock/__init__.py
odoo/addons/project_stock/__manifest__.py
odoo/addons/project_stock/i18n/es.po
odoo/addons/project_stock/i18n/project_stock.pot
odoo/addons/project_stock/migrations/13.0.2.0.0/post-migration.py
odoo/addons/project_stock/models/__init__.py
odoo/addons/project_stock/models/account_analytic_line.py
odoo/addons/project_stock/models/project_project.py
odoo/addons/project_stock/models/project_task.py
odoo/addons/project_stock/models/stock_move.py
odoo/addons/project_stock/models/stock_scrap.py
odoo/addons/project_stock/readme/CONFIGURE.rst
odoo/addons/project_stock/readme/CONTRIBUTORS.rst
odoo/addons/project_stock/readme/DESCRIPTION.rst
odoo/addons/project_stock/readme/USAGE.rst
odoo/addons/project_stock/static/description/icon.png
odoo/addons/project_stock/static/description/index.html
odoo/addons/project_stock/tests/__init__.py
odoo/addons/project_stock/tests/common.py
odoo/addons/project_stock/tests/test_project_stock.py
odoo/addons/project_stock/views/project_project_view.xml
odoo/addons/project_stock/views/project_task_type_view.xml
odoo/addons/project_stock/views/project_task_view.xml
odoo/addons/project_stock/views/stock_move_view.xml
odoo13_addon_project_stock-13.0.2.2.3.dist-info/METADATA
odoo13_addon_project_stock-13.0.2.2.3.dist-info/WHEEL
odoo13_addon_project_stock-13.0.2.2.3.dist-info/top_level.txt
odoo13_addon_project_stock-13.0.2.2.3.dist-info/RECORD
